crony/__init__.py
crony/__main__.py
crony/crony.py
crony-0.2.1.dist-info/DESCRIPTION.rst
crony-0.2.1.dist-info/METADATA
crony-0.2.1.dist-info/RECORD
crony-0.2.1.dist-info/WHEEL
crony-0.2.1.dist-info/entry_points.txt
crony-0.2.1.dist-info/metadata.json
crony-0.2.1.dist-info/top_level.txt
