Metadata-Version: 2.0
Name: crony
Version: 0.2.1
Summary: Cron monitoring tool.
Home-page: https://github.com/youversion/crony
Author: Brad Belyeu
Author-email: brad.belyeu@life.church
License: MIT
Download-URL: https://github.com/youversion/crony/archive/0.2.1.zip
Keywords: cron,monitoring,sentry.io,cronitor.io
Platform: unix
Platform: mac
Classifier: Environment :: Console
Classifier: Intended Audience :: Developers
Classifier: Intended Audience :: Information Technology
Classifier: Intended Audience :: System Administrators
Classifier: License :: OSI Approved :: MIT License
Classifier: Operating System :: Unix
Classifier: Programming Language :: Python
Classifier: Programming Language :: Python :: 3
Classifier: Topic :: Software Development :: Libraries :: Python Modules
Classifier: Topic :: System :: Monitoring
Classifier: Topic :: Utilities
Requires-Dist: raven (>=6.1.0)
Requires-Dist: requests (>=2.18.4)
